nasalib/__init__.py
nasalib/dataframe_utils.py
nasalib/nasa_parser.py
tests/__init__.py
nasaparser-0.1.0.dist-info/METADATA
nasaparser-0.1.0.dist-info/WHEEL
nasaparser-0.1.0.dist-info/top_level.txt
nasaparser-0.1.0.dist-info/RECORD
