Metadata-Version: 2.4
Name: nasaparser
Version: 0.1.0
Summary: NASA (Need Analysis)PDF Parser Library for extracting structured data
Home-page: https://github.com/rawsid11/nasaparser
Author: Siddhesh Phapale
Author-email: rawsiddhesh11@gmail.com
Classifier: Programming Language :: Python :: 3
Classifier: License :: OSI Approved :: MIT License
Classifier: Operating System :: OS Independent
Requires-Python: >=3.10
Requires-Dist: pdfplumber>=0.7.0
Requires-Dist: pandas>=1.3.0
Dynamic: author
Dynamic: author-email
Dynamic: classifier
Dynamic: description
Dynamic: description-content-type
Dynamic: home-page
Dynamic: requires-dist
Dynamic: requires-python
Dynamic: summary
